pymodularizer/__init__.py
pymodularizer/__main__.py
pymodularizer/core/__init__.py
pymodularizer/core/cli.py
pymodularizer/core/default_config.py
pymodularizer/core/generator.py
pymodularizer/core/utils.py
pymodularizer/helpers/__init__.py
pymodularizer/helpers/files.py
pymodularizer/helpers/module.py
pymodularizer/models/fastapi_api.json
pymodularizer/models/flask_api.json
pymodularizer/models/kyvi_app.json
pymodularizer/models/modular_application.json
pymodularizer/models/python_package.json
pymodularizer/models/simple_script.json
pymodularizer-1.0.3.dist-info/licenses/LICENSE
pymodularizer-1.0.3.dist-info/METADATA
pymodularizer-1.0.3.dist-info/WHEEL
pymodularizer-1.0.3.dist-info/entry_points.txt
pymodularizer-1.0.3.dist-info/top_level.txt
pymodularizer-1.0.3.dist-info/RECORD
