Metadata-Version: 2.4
Name: pymodularizer
Version: 1.0.3
Summary: Gerador de projetos Python modularizados
Author: Hermes A. V. Urquijo
Author-email: "Hermes A. V. Urquijo" <hvurquijo@gmail.com>
License: MIT License
Requires-Python: >=3.8
License-File: LICENSE
Requires-Dist: typer[all]
Dynamic: license-file
